bing_translation_for_python/__init__.py
bing_translation_for_python/core.py
bing_translation_for_python/setting.py
bing_translation_for_python/public/__init__.py
bing_translation_for_python/public/errors.py
test/__init__.py
test/config_test.py
test/core_test.py
test/error_test.py
bing_translation_for_python-3.0.2.dist-info/LICENSE
bing_translation_for_python-3.0.2.dist-info/METADATA
bing_translation_for_python-3.0.2.dist-info/WHEEL
bing_translation_for_python-3.0.2.dist-info/top_level.txt
bing_translation_for_python-3.0.2.dist-info/RECORD
