Metadata-Version: 2.1
Name: bing-translation-for-python
Version: 3.0.2
Summary: Bing translation for python
Home-page: UNKNOWN
Author: 87Keys
Author-email: meme_me2019@outlook.com
License: UNKNOWN
Platform: UNKNOWN
Classifier: Programming Language :: Python
Classifier: Programming Language :: Python :: 3
Classifier: Programming Language :: Python :: 3 :: Only
Classifier: Programming Language :: Python :: 3.6
Classifier: Programming Language :: Python :: 3.7
Classifier: Programming Language :: Python :: 3.8
Classifier: Programming Language :: Python :: 3.9
Classifier: Topic :: Software Development :: Libraries :: Python Modules
Requires-Python: >=3.6
License-File: LICENSE
Requires-Dist: requests
Requires-Dist: tqdm
Requires-Dist: bs4
